request_url_2023/__init__.py
request_url_2023/send_requests.py
request_url_2023-1.0.3.dist-info/LICENSE
request_url_2023-1.0.3.dist-info/METADATA
request_url_2023-1.0.3.dist-info/WHEEL
request_url_2023-1.0.3.dist-info/top_level.txt
request_url_2023-1.0.3.dist-info/RECORD
